KittenScript/__init__.py
KittenScript/__main__.py
KittenScript/ide.py
KittenScript/ide_cn.py
KittenScript/stdio.py
KittenScript/version.py
KittenScript/src/__init__.py
KittenScript/src/basic.py
KittenScript/src/constants.py
KittenScript/src/errors.py
KittenScript/src/tokens.py
KittenScript/src/interpreter/__init__.py
KittenScript/src/interpreter/context.py
KittenScript/src/interpreter/interpreter.py
KittenScript/src/interpreter/table.py
KittenScript/src/interpreter/values.py
KittenScript/src/interpreter/lib/__init__.py
KittenScript/src/interpreter/lib/_sort.py
KittenScript/src/interpreter/lib/heap.kst
KittenScript/src/interpreter/lib/math.kst
KittenScript/src/interpreter/lib/object.py
KittenScript/src/interpreter/lib/python.py
KittenScript/src/interpreter/lib/randoms.py
KittenScript/src/interpreter/lib/sort.kst
KittenScript/src/interpreter/lib/timelib.py
KittenScript/src/lexer/__init__.py
KittenScript/src/lexer/lexer.py
KittenScript/src/lexer/position.py
KittenScript/src/parse/GRAMMER.bnf
KittenScript/src/parse/__init__.py
KittenScript/src/parse/nodes.py
KittenScript/src/parse/parser.py
KittenScript-1.2.1.dist-info/LICENSE
KittenScript-1.2.1.dist-info/METADATA
KittenScript-1.2.1.dist-info/WHEEL
KittenScript-1.2.1.dist-info/top_level.txt
KittenScript-1.2.1.dist-info/RECORD
